desbordante.cpython-312-darwin.so
desbordante-2.4.0.dist-info/RECORD
desbordante-2.4.0.dist-info/WHEEL
desbordante-2.4.0.dist-info/METADATA
desbordante-2.4.0.dist-info/licenses/COPYING
desbordante.dylibs/libboost_thread.dylib
desbordante.dylibs/libboost_graph.dylib
desbordante.dylibs/libboost_container.dylib
desbordante.dylibs/libboost_regex.dylib
