Metadata-Version: 2.2
Name: desbordante
Version: 2.4.0
Summary: Science-intensive high-performance data profiler
License: AGPL-3.0-only
Classifier: License :: OSI Approved :: GNU Affero General Public License v3
Classifier: Operating System :: POSIX :: Linux
Classifier: Operating System :: MacOS :: MacOS X
Classifier: Programming Language :: Python :: 3.8
Classifier: Programming Language :: Python :: 3.9
Classifier: Programming Language :: Python :: 3.10
Classifier: Programming Language :: Python :: 3.11
Classifier: Programming Language :: Python :: 3.12
Classifier: Programming Language :: Python :: 3.13
Classifier: Topic :: Scientific/Engineering
Classifier: Topic :: Software Development :: Libraries :: Python Modules
Project-URL: homepage, https://desbordante.unidata-platform.ru/
Project-URL: repository, https://github.com/desbordante/desbordante-core
Project-URL: issues, https://github.com/desbordante/desbordante-core/issues
Requires-Python: >=3.8
